tajweed_embeddings/__init__.py
tajweed_embeddings/data/sifat.json
tajweed_embeddings/embedder/__init__.py
tajweed_embeddings/embedder/cli.py
tajweed_embeddings/embedder/harakat_embedder.py
tajweed_embeddings/embedder/letters_embedder.py
tajweed_embeddings/embedder/sifat_editor.py
tajweed_embeddings/embedder/sifat_embedder.py
tajweed_embeddings/embedder/tajweed_embedder.py
tajweed_embeddings/embedder/tajweed_rules_embedder.py
tajweed_embeddings/rules_gen/__init__.py
tajweed_embeddings/rules_gen/tajweed_classifier.py
tajweed_embeddings/rules_gen/tree.py
tajweed_embeddings/rules_gen/rule_trees/ghunnah.end.json
tajweed_embeddings/rules_gen/rule_trees/ghunnah.start.json
tajweed_embeddings/rules_gen/rule_trees/ghunnah_tafkheem.end.json
tajweed_embeddings/rules_gen/rule_trees/ghunnah_tafkheem.start.json
tajweed_embeddings/rules_gen/rule_trees/hamzat_wasl.end.json
tajweed_embeddings/rules_gen/rule_trees/hamzat_wasl.start.json
tajweed_embeddings/rules_gen/rule_trees/idghaam_ghunnah.end.json
tajweed_embeddings/rules_gen/rule_trees/idghaam_ghunnah.start.json
tajweed_embeddings/rules_gen/rule_trees/idghaam_mutajanisayn.end.json
tajweed_embeddings/rules_gen/rule_trees/idghaam_mutajanisayn.start.json
tajweed_embeddings/rules_gen/rule_trees/idghaam_mutaqaribayn.end.json
tajweed_embeddings/rules_gen/rule_trees/idghaam_mutaqaribayn.start.json
tajweed_embeddings/rules_gen/rule_trees/idghaam_no_ghunnah.end.json
tajweed_embeddings/rules_gen/rule_trees/idghaam_no_ghunnah.start.json
tajweed_embeddings/rules_gen/rule_trees/idghaam_shafawi.end.json
tajweed_embeddings/rules_gen/rule_trees/idghaam_shafawi.start.json
tajweed_embeddings/rules_gen/rule_trees/ikhfa.end.json
tajweed_embeddings/rules_gen/rule_trees/ikhfa.start.json
tajweed_embeddings/rules_gen/rule_trees/ikhfa_shafawi.end.json
tajweed_embeddings/rules_gen/rule_trees/ikhfa_shafawi.start.json
tajweed_embeddings/rules_gen/rule_trees/iqlab.end.json
tajweed_embeddings/rules_gen/rule_trees/iqlab.start.json
tajweed_embeddings-1.0.8.dist-info/licenses/LICENSE
tajweed_embeddings-1.0.8.dist-info/METADATA
tajweed_embeddings-1.0.8.dist-info/WHEEL
tajweed_embeddings-1.0.8.dist-info/entry_points.txt
tajweed_embeddings-1.0.8.dist-info/top_level.txt
tajweed_embeddings-1.0.8.dist-info/RECORD
