Metadata-Version: 2.4
Name: tajweed-embeddings
Version: 1.0.8
Summary: Quran Tajweed Embeddings Generator
Author: Tarek Eldeeb
Requires-Python: >=3.10
License-File: LICENSE
Requires-Dist: numpy>=1.26
Provides-Extra: test
Requires-Dist: pytest>=7.4; extra == "test"
Dynamic: license-file
